odoo/addons/l10n_it_edi_extension/README.rst
odoo/addons/l10n_it_edi_extension/__init__.py
odoo/addons/l10n_it_edi_extension/__manifest__.py
odoo/addons/l10n_it_edi_extension/controllers/__init__.py
odoo/addons/l10n_it_edi_extension/controllers/portal.py
odoo/addons/l10n_it_edi_extension/data/FoglioStileAssoSoftware.xsl
odoo/addons/l10n_it_edi_extension/data/invoice_it_template.xml
odoo/addons/l10n_it_edi_extension/data/res.city.it.code.csv
odoo/addons/l10n_it_edi_extension/i18n/it.po
odoo/addons/l10n_it_edi_extension/i18n/l10n_it_edi_extension.pot
odoo/addons/l10n_it_edi_extension/i18n/l10n_it_edi_fatturapa.pot
odoo/addons/l10n_it_edi_extension/models/__init__.py
odoo/addons/l10n_it_edi_extension/models/account_journal.py
odoo/addons/l10n_it_edi_extension/models/account_move.py
odoo/addons/l10n_it_edi_extension/models/account_move_line.py
odoo/addons/l10n_it_edi_extension/models/ir_attachment.py
odoo/addons/l10n_it_edi_extension/models/l10n_it_edi_activity_progress.py
odoo/addons/l10n_it_edi_extension/models/l10n_it_edi_article_code.py
odoo/addons/l10n_it_edi_extension/models/l10n_it_edi_discount_rise_price.py
odoo/addons/l10n_it_edi_extension/models/l10n_it_edi_line.py
odoo/addons/l10n_it_edi_extension/models/l10n_it_edi_line_other_data.py
odoo/addons/l10n_it_edi_extension/models/l10n_it_edi_summary_data.py
odoo/addons/l10n_it_edi_extension/models/res_city_it_code.py
odoo/addons/l10n_it_edi_extension/models/res_company.py
odoo/addons/l10n_it_edi_extension/models/res_partner.py
odoo/addons/l10n_it_edi_extension/readme/CONFIGURE.md
odoo/addons/l10n_it_edi_extension/readme/CONTRIBUTORS.md
odoo/addons/l10n_it_edi_extension/readme/DESCRIPTION.md
odoo/addons/l10n_it_edi_extension/security/ir.model.access.csv
odoo/addons/l10n_it_edi_extension/static/description/icon.png
odoo/addons/l10n_it_edi_extension/static/description/index.html
odoo/addons/l10n_it_edi_extension/tests/__init__.py
odoo/addons/l10n_it_edi_extension/tests/common.py
odoo_addon_l10n_it_edi_extension-18.0.1.2.0.dist-info/METADATA
odoo_addon_l10n_it_edi_extension-18.0.1.2.0.dist-info/WHEEL
odoo_addon_l10n_it_edi_extension-18.0.1.2.0.dist-info/top_level.txt
odoo_addon_l10n_it_edi_extension-18.0.1.2.0.dist-info/RECORD
