Metadata-Version: 2.1
Name: odoo-addon-l10n_it_edi_extension
Version: 18.0.1.2.0
Requires-Python: >=3.10
Requires-Dist: codicefiscale
Requires-Dist: odoo-addon-partner_firstname==18.0.*
Requires-Dist: odoo==18.0.*
Requires-Dist: openupgradelib
Summary: E-invoice base feature
Home-page: https://github.com/OCA/l10n-italy
License: AGPL-3
Author: Giuseppe Borruso, Odoo Community Association (OCA)
Author-email: support@odoo-community.org
Classifier: Programming Language :: Python
Classifier: Framework :: Odoo
Classifier: Framework :: Odoo :: 18.0
Classifier: License :: OSI Approved :: GNU Affero General Public License v3
Classifier: Development Status :: 4 - Beta
